djangoldp_like/__init__.py
djangoldp_like/admin.py
djangoldp_like/apps.py
djangoldp_like/factories.py
djangoldp_like/models.py
djangoldp_like/management/__init__.py
djangoldp_like/management/commands/__init__.py
djangoldp_like/management/commands/mock_example.py
djangoldp_like/migrations/0001_initial.py
djangoldp_like/migrations/__init__.py
djangoldp_like-0.0.3.dist-info/METADATA
djangoldp_like-0.0.3.dist-info/WHEEL
djangoldp_like-0.0.3.dist-info/top_level.txt
djangoldp_like-0.0.3.dist-info/RECORD
