Metadata-Version: 2.1
Name: djangoldp-like
Version: 0.0.3
Summary: DjangoLDP Like
Home-page: http://git.happy-dev.fr/startinblox/djangoldp-packages/djangoldp-like
Author: Startin'blox
Author-email: benoit@paris.happy-dev.fr
License: MIT
Platform: UNKNOWN
Classifier: Programming Language :: Python :: 3
Requires-Dist: djangoldp (~=0.5)
